ismartcsv/__init__.py
ismartcsv/config_parser.py
ismartcsv/configuration.py
ismartcsv/dataset.py
ismartcsv/formatters.py
ismartcsv/plotting.py
ismartcsv/utilities.py
ismartcsv/version.py
ismartcsv-1.0.9.data/scripts/idatfile_creator
ismartcsv-1.0.9.dist-info/LICENSE
ismartcsv-1.0.9.dist-info/METADATA
ismartcsv-1.0.9.dist-info/WHEEL
ismartcsv-1.0.9.dist-info/top_level.txt
ismartcsv-1.0.9.dist-info/RECORD
