Metadata-Version: 2.1
Name: ismartcsv
Version: 1.0.9
Summary: ismartcsv - smart way to handle scientific instrument generated csv files
Home-page: https://github.com/jeldikk/ismartcsv
Author: jeldikk
Author-email: jeldi.kamal2013@gmail.com
License: UNKNOWN
Platform: UNKNOWN
Classifier: Programming Language :: Python :: 3
Classifier: Operating System :: OS Independent
Requires-Python: >=3.6
Requires-Dist: numpy
Requires-Dist: matplotlib
Requires-Dist: pyYAML
